synctodoist/__init__.py
synctodoist/exceptions.py
synctodoist/managers/__init__.py
synctodoist/managers/base_manager.py
synctodoist/managers/command_manager.py
synctodoist/managers/label_manager.py
synctodoist/managers/project_manager.py
synctodoist/managers/reminder_manager.py
synctodoist/managers/section_manager.py
synctodoist/managers/task_manager.py
synctodoist/models/__init__.py
synctodoist/models/command.py
synctodoist/models/due.py
synctodoist/models/enums.py
synctodoist/models/label.py
synctodoist/models/project.py
synctodoist/models/reminder.py
synctodoist/models/section.py
synctodoist/models/settings.py
synctodoist/models/task.py
synctodoist/models/todoist_base_model.py
synctodoist/models/utils.py
synctodoist/todoist_api.py
synctodoist-0.3.5.dist-info/LICENSE.md
synctodoist-0.3.5.dist-info/METADATA
synctodoist-0.3.5.dist-info/WHEEL
synctodoist-0.3.5.dist-info/entry_points.txt
synctodoist-0.3.5.dist-info/RECORD
