Metadata-Version: 2.1
Name: synctodoist
Version: 0.3.5
Summary: A Python wrapper for the Todoist Sync API v9
Home-page: https://github.com/gaborschulz/synctodoist
License: MIT
Author: Gabor Schulz
Requires-Python: >=3.10
Classifier: Development Status :: 3 - Alpha
Classifier: License :: OSI Approved :: MIT License
Classifier: Natural Language :: English
Classifier: Programming Language :: Python
Classifier: Programming Language :: Python :: 3
Classifier: Programming Language :: Python :: 3.10
Classifier: Programming Language :: Python :: 3.11
Classifier: Programming Language :: Python :: 3.12
Classifier: Programming Language :: Python :: 3 :: Only
Requires-Dist: httpx (>=0.23.1,<0.24.0)
Requires-Dist: isort (>=5.13.2,<6.0.0)
Requires-Dist: pydantic (>=2.5.3,<3.0.0)
Requires-Dist: pydantic-settings (>=2.1.0,<3.0.0)
Requires-Dist: python-dotenv (>=0.21.0,<0.22.0)
Project-URL: Documentation, https://github.com/gaborschulz/synctodoist
Project-URL: Repository, https://github.com/gaborschulz/synctodoist
